threadyq/__init__.py
threadyq/threadyq.py
threadyq-1.0.14.dist-info/LICENSE
threadyq-1.0.14.dist-info/METADATA
threadyq-1.0.14.dist-info/WHEEL
threadyq-1.0.14.dist-info/top_level.txt
threadyq-1.0.14.dist-info/RECORD
