Metadata-Version: 2.1
Name: threadyq
Version: 1.0.14
Summary: ThreadyQ is a Python library designed to simplify and extend the capabilities of threading and queue management. This package provides an abstraction layer over Python's built-in threading and queue modules, enabling developers to create, manage, and synchronize tasks efficiently in multi-threaded applications.
Home-page: https://github.com/muhammedrahil/ThreadyQ
Author: Muhammed Rahil M
Author-email: muhammedrahilmadathingal@gmail.com
Keywords: python,threading,queue
Classifier: Development Status :: 1 - Planning
Classifier: Intended Audience :: Developers
Classifier: Programming Language :: Python :: 3.11
Classifier: Operating System :: OS Independent
Classifier: License :: OSI Approved :: MIT License
License-File: LICENSE
